qof/__init__.py
qof/__main__.py
qof/app.py
qof/cli.py
qof/resources/README
qof/resources/icon.icns
qof/resources/icon.ico
qof/resources/stylesheets/dark.txt
qof/resources/stylesheets/light.txt
qof-1.2.0.dist-info/licenses/LICENSE
qof-1.2.0.dist-info/METADATA
qof-1.2.0.dist-info/WHEEL
qof-1.2.0.dist-info/entry_points.txt
qof-1.2.0.dist-info/top_level.txt
qof-1.2.0.dist-info/RECORD
