Metadata-Version: 2.4
Name: qof
Version: 1.2.0
Summary: qof | Quickly Organize Files!
Author-email: devs_des1re <arjunbrij8811@gmail.com>, Eivind Teig <eivind.teig@gmail.com>
Maintainer-email: devs_des1re <arjunbrij8811@gmail.com>
License-Expression: MIT
Keywords: app,macOS,windows,linux,flatpak
Classifier: Development Status :: 4 - Beta
Classifier: Intended Audience :: Developers
Classifier: Operating System :: OS Independent
Classifier: Programming Language :: Python :: 3
Classifier: Programming Language :: Python :: 3.10
Classifier: Programming Language :: Python :: 3.11
Classifier: Programming Language :: Python :: 3.12
Classifier: Programming Language :: Python :: 3.13
Classifier: Programming Language :: Python :: 3.14
Classifier: Programming Language :: Python :: 3 :: Only
Classifier: Topic :: Software Development
Classifier: Topic :: Utilities
Requires-Python: >=3.10
License-File: LICENSE
Requires-Dist: pip>=21.2
Requires-Dist: PySide6-Essentials>=6.9.2
Requires-Dist: darkdetect>=0.8.0
Requires-Dist: typer~=0.16
Dynamic: license-file
